qapp_cuda_quantum/async_tasks/__init__.py
qapp_cuda_quantum/async_tasks/cuda_quantum_circuit_export_task.py
qapp_cuda_quantum/component/__init__.py
qapp_cuda_quantum/component/backend/__init__.py
qapp_cuda_quantum/component/backend/cuda_quantum_invocation.py
qapp_cuda_quantum/factory/__init__.py
qapp_cuda_quantum/factory/cuda_quantum_device_factory.py
qapp_cuda_quantum/factory/cuda_quantum_handler_factory.py
qapp_cuda_quantum/factory/cuda_quantum_provider_factory.py
qapp_cuda_quantum/handler/__init__.py
qapp_cuda_quantum/handler/invocation_handler.py
qapp_cuda_quantum/model/__init__.py
qapp_cuda_quantum/model/device/__init__.py
qapp_cuda_quantum/model/device/qapp_cuda_quantum_device.py
qapp_cuda_quantum/model/provider/__init__.py
qapp_cuda_quantum/model/provider/qapp_cuda_quantum_provider.py
qapp_cuda_quantum-0.0.2.dist-info/METADATA
qapp_cuda_quantum-0.0.2.dist-info/WHEEL
qapp_cuda_quantum-0.0.2.dist-info/top_level.txt
qapp_cuda_quantum-0.0.2.dist-info/RECORD
