Metadata-Version: 2.1
Name: qapp-cuda-quantum
Version: 0.0.2
Summary: QApp pennylane library supporting QApp Platform for Quantum Computing
Author-email: "CITYNOW Co. Ltd. " <corp@citynow.vn>
Project-URL: Homepage, https://citynow.asia/
Keywords: qapp,qapp-cuda-quantum,cuda-quamtum,quantum
Classifier: License :: OSI Approved :: MIT License
Classifier: Programming Language :: Python
Classifier: Programming Language :: Python :: 3
Requires-Python: >=3.10
Requires-Dist: qapp-common==0.0.8.2
Requires-Dist: cuda-quantum==0.8.0
Provides-Extra: dev
Requires-Dist: black; extra == "dev"
Requires-Dist: bumpver; extra == "dev"
Requires-Dist: isort; extra == "dev"
Requires-Dist: pip-tools; extra == "dev"
Requires-Dist: pytest; extra == "dev"
